lmstudio_wrapper/__init__.py
lmstudio_wrapper/client.py
lmstudio_wrapper/exceptions.py
lmstudio_wrapper/utils.py
lmstudio_wrapper-0.1.4.dist-info/METADATA
lmstudio_wrapper-0.1.4.dist-info/WHEEL
lmstudio_wrapper-0.1.4.dist-info/top_level.txt
lmstudio_wrapper-0.1.4.dist-info/RECORD
