Metadata-Version: 2.2
Name: lmstudio-wrapper
Version: 0.1.4
Summary: A client library for interacting with the LM Studio API
Home-page: https://github.com/harshitkumar9030/lmstudio-client
Author: Harshit
Author-email: harshitkumar9030@gmail.com
Classifier: Programming Language :: Python :: 3
Classifier: License :: OSI Approved :: MIT License
Classifier: Operating System :: OS Independent
Classifier: Development Status :: 4 - Beta
Classifier: Intended Audience :: Developers
Classifier: Topic :: Software Development :: Libraries :: Python Modules
Requires-Python: >=3.6
Requires-Dist: requests>=2.25.0
Dynamic: author
Dynamic: author-email
Dynamic: classifier
Dynamic: description
Dynamic: description-content-type
Dynamic: home-page
Dynamic: requires-dist
Dynamic: requires-python
Dynamic: summary
